NumberGenerate/IDCard.py
NumberGenerate/Name.py
NumberGenerate/Phone.py
NumberGenerate/SaveFile.py
NumberGenerate/User.py
NumberGenerate/__init__.py
NumberGenerate/errors.py
NumberGenerate/api/__init__.py
NumberGenerate/api/get_phone_api.py
NumberGenerate/db/__init__.py
NumberGenerate/db/area_code.db
NumberGenerate/db/csv_db.py
NumberGenerate/db/dat_csv.py
NumberGenerate-0.1.3.dist-info/METADATA
NumberGenerate-0.1.3.dist-info/WHEEL
NumberGenerate-0.1.3.dist-info/top_level.txt
NumberGenerate-0.1.3.dist-info/RECORD
