Metadata-Version: 2.1
Name: NumberGenerate
Version: 0.1.3
Summary: CN-NumberGenerate
Home-page: https://github.com/FourTwooo/NumberGenerate
Author: 42
Author-email: 1666671111@qq.com
Classifier: Programming Language :: Python :: 3
Requires-Python: >=3.6
Requires-Dist: certifi==2024.8.30
Requires-Dist: charset-normalizer==3.4.0
Requires-Dist: idna==3.10
Requires-Dist: lunardate==0.2.2
Requires-Dist: pypinyin==0.53.0
Requires-Dist: requests==2.32.3
